xfsystem/__init__.py
xfsystem/dataframe_transformers.py
xfsystem/date_helper.py
xfsystem/dateframe_util.py
xfsystem/odk_api_connector.py
xfsystem/pandas_to_pyspark.py
xfsystem/postgres_helper.py
xfsystem/spark_helper.py
xfsystem/sqlserver_helper.py
xfsystem-0.0.2.dist-info/LICENSE
xfsystem-0.0.2.dist-info/METADATA
xfsystem-0.0.2.dist-info/WHEEL
xfsystem-0.0.2.dist-info/top_level.txt
xfsystem-0.0.2.dist-info/RECORD
